{
  "Projects": [
    {
      "title": "3D Animation",
      "year": 2021,
      "tools": [ "Autodesk Maya", "Adobe Substance 3D Painter", "Adobe Premiere Pro", "Quixel Mixer", "Quixel Bridge" ],
      "media": [
        {
          "Image": "../../../assets/ProjectsImage/ThreeDArt/Growth/Growth01.gif"
        },
        {
          "Video": "https://www.youtube.com/embed/1LInSFfMVyM"
        }
      ],
      "overview": "This is a 3D animation depicting a robot, inspired by the one from the movie 'Castle in the Sky,' protecting a growing tree.",
      "link": "projectOne.com"
    },
    {
      "title": "3D Model (Movie Vehicle)",
      "year": 2021,
      "tools": [ "Autodesk 3ds Max", "Adobe Substance 3D Painter", "Adobe Photoshop" ],
      "media": [
        {
          "Image": "../../../assets/ProjectsImage/ThreeDArt/LEGO/LEGO01.jpg"
        },
        {
          "Image": "../../../assets/ProjectsImage/ThreeDArt/LEGO/LEGO02.jpg"
        },
        {
          "Image": "../../../assets/ProjectsImage/ThreeDArt/LEGO/LEGO03.jpg"
        },
        {
          "Image": "../../../assets/ProjectsImage/ThreeDArt/LEGO/LEGO04.jpg"
        },
        {
          "Image": "../../../assets/ProjectsImage/ThreeDArt/LEGO/LEGO05.jpg"
        },
        {
          "Image": "../../../assets/ProjectsImage/ThreeDArt/LEGO/LEGO06.jpg"
        },
        {
          "Image": "../../../assets/ProjectsImage/ThreeDArt/LEGO/LEGO07.jpg"
        },
        {
          "Image": "../../../assets/ProjectsImage/ThreeDArt/LEGO/LEGO08.jpg"
        }
      ],
      "overview": "This is a 3D model of a LEGO version of the Star Wars A-wing starfighter.",
      "link": "projectTwo.github.com"
    },
    {
      "title": "3D Model (Game Character)",
      "year": 2020,
      "tools": [ "Autodesk Maya", "Adobe Substance 3D Painter" ],
      "media": [
        {
          "Image": "../../../assets/ProjectsImage/ThreeDArt/DVAMech/DVAMech01.jpg"
        },
        {
          "Image": "../../../assets/ProjectsImage/ThreeDArt/DVAMech/DVAMech02.jpg"
        }
      ],
      "overview": "This is a 3D model of D.Va's mech, which comes from a video game called Overwatch.",
      "link": "project3.github.com"
    }
  ]
}